dvc_studio_client/__init__.py
dvc_studio_client/auth.py
dvc_studio_client/config.py
dvc_studio_client/env.py
dvc_studio_client/model_registry.py
dvc_studio_client/post_live_metrics.py
dvc_studio_client/py.typed
dvc_studio_client/schema.py
dvc_studio_client-0.21.0.dist-info/LICENSE
dvc_studio_client-0.21.0.dist-info/METADATA
dvc_studio_client-0.21.0.dist-info/WHEEL
dvc_studio_client-0.21.0.dist-info/top_level.txt
dvc_studio_client-0.21.0.dist-info/RECORD
