Metadata-Version: 2.1
Name: dvc-studio-client
Version: 0.21.0
Summary: Small library to post data from DVC/DVCLive to Iterative Studio 
Author-email: Iterative <support@dvc.org>
License: Apache-2.0
Project-URL: Issues, https://github.com/iterative/dvc-studio-client/issues
Project-URL: Source, https://github.com/iterative/dvc-studio-client
Classifier: Programming Language :: Python :: 3
Classifier: Programming Language :: Python :: 3.9
Classifier: Programming Language :: Python :: 3.10
Classifier: Programming Language :: Python :: 3.11
Classifier: Programming Language :: Python :: 3.12
Classifier: Development Status :: 1 - Planning
Requires-Python: >=3.9
License-File: LICENSE
Requires-Dist: dulwich
Requires-Dist: requests
Requires-Dist: voluptuous
Provides-Extra: docs
Requires-Dist: mkdocs<2,>=1.5.2; extra == "docs"
Requires-Dist: mkdocs-gen-files<1,>=0.5.0; extra == "docs"
Requires-Dist: mkdocs-material<10,>=9.3.1; extra == "docs"
Requires-Dist: mkdocs-section-index<1,>=0.3.6; extra == "docs"
Requires-Dist: mkdocstrings-python<2,>=1.6.3; extra == "docs"
Provides-Extra: tests
Requires-Dist: pytest<9,>=7; extra == "tests"
Requires-Dist: pytest-cov>=4.1.0; extra == "tests"
Requires-Dist: pytest-sugar; extra == "tests"
Requires-Dist: pytest-mock; extra == "tests"
Provides-Extra: dev
Requires-Dist: dvc-studio-client[docs,tests]; extra == "dev"
Requires-Dist: types-requests; extra == "dev"
Requires-Dist: mypy==1.10.1; extra == "dev"
